dash_disable_devtool_plugin/__init__.py
dash_disable_devtool_plugin-0.1.1.dist-info/licenses/LICENSE
dash_disable_devtool_plugin-0.1.1.dist-info/METADATA
dash_disable_devtool_plugin-0.1.1.dist-info/WHEEL
dash_disable_devtool_plugin-0.1.1.dist-info/top_level.txt
dash_disable_devtool_plugin-0.1.1.dist-info/RECORD
